p2pchat/__init__.py
p2pchat/bot.py
p2pchat/client.py
p2pchat/commands.py
p2pchat/events.py
p2pchat/api/__init__.py
p2pchat/api/endpoints.py
p2pchat/utils/__init__.py
p2pchat/utils/helpers.py
p2pchat-0.1.31.dist-info/licenses/LICENSE
p2pchat-0.1.31.dist-info/METADATA
p2pchat-0.1.31.dist-info/WHEEL
p2pchat-0.1.31.dist-info/top_level.txt
p2pchat-0.1.31.dist-info/RECORD
