Metadata-Version: 2.4
Name: p2pchat
Version: 0.1.31
License-File: LICENSE
Requires-Dist: aiohttp
Requires-Dist: asyncio
Dynamic: license-file
Dynamic: requires-dist
